pyserilog_logging_handler/__init__.py
pyserilog_logging_handler/handler.py
pyserilog_logging_handler-0.2.1.dist-info/LICENSE
pyserilog_logging_handler-0.2.1.dist-info/METADATA
pyserilog_logging_handler-0.2.1.dist-info/WHEEL
pyserilog_logging_handler-0.2.1.dist-info/top_level.txt
pyserilog_logging_handler-0.2.1.dist-info/RECORD
